TopsisSimranjit102017060/__init__.py
TopsisSimranjit102017060/__main__.py
TopsisSimranjit102017060-2.0.0.dist-info/LICENSE
TopsisSimranjit102017060-2.0.0.dist-info/METADATA
TopsisSimranjit102017060-2.0.0.dist-info/WHEEL
TopsisSimranjit102017060-2.0.0.dist-info/top_level.txt
TopsisSimranjit102017060-2.0.0.dist-info/RECORD
