Metadata-Version: 2.1
Name: TopsisSimranjit102017060
Version: 2.0.0
Summary: Python library for dealing with Multiple Criteria Decision Making(MCDM) problems
Home-page: https://github.com/S03imran/Topsis.git
Author: Simranjit Kaur
Author-email: s03imran@gmail.com
License: MIT
Classifier: License :: OSI Approved :: MIT License
Classifier: Programming Language :: Python :: 3.6
Classifier: Programming Language :: Python :: 3.7
Classifier: Programming Language :: Python :: 3.8
License-File: LICENSE
